{
    "elevenlabs": {
        "apiKey": "your-api-key-here",
        "voiceId": "your-voice-id-here",
        "modelId": "eleven_monolingual_v1",
        "agentId": "your-agent-id-here-optional",
        "language": "en-US",
        "additionalParams": {
            "stability": 0.5,
            "similarity_boost": 0.75,
            "style": 0.0,
            "use_speaker_boost": true
        }
    },
    "speech": {
        "language": "en-US",
        "continuous": false,
        "interimResults": false
    }
} 